redmind/__init__.py
redmind/dataloader.py
redmind/functions.py
redmind/layers.py
redmind/loss.py
redmind/network.py
redmind/normalizer.py
redmind/optimizers.py
redmind/trainer.py
redmind/utils.py
redmind-0.0.9.dist-info/LICENSE
redmind-0.0.9.dist-info/METADATA
redmind-0.0.9.dist-info/WHEEL
redmind-0.0.9.dist-info/top_level.txt
redmind-0.0.9.dist-info/RECORD
