Metadata-Version: 2.1
Name: redmind
Version: 0.0.9
Summary: Package for building Machine learning models
Home-page: UNKNOWN
Author: Diego Velez
Author-email: diegovelezs94@gmail.com
License: UNKNOWN
Keywords: python,ai,machine learning,neural network
Platform: UNKNOWN
Classifier: Development Status :: 1 - Planning
Classifier: Intended Audience :: Developers
Classifier: Programming Language :: Python :: 3
Classifier: Operating System :: Unix
Classifier: Operating System :: MacOS :: MacOS X
Classifier: Operating System :: Microsoft :: Windows
Requires-Dist: numpy
Requires-Dist: matplotlib
Requires-Dist: dill
Requires-Dist: pandas
Requires-Dist: torch
